primfunctions/__init__.py
primfunctions/cache.py
primfunctions/configuration.py
primfunctions/context.py
primfunctions/events.py
primfunctions/logger.py
primfunctions/test_runner.py
primfunctions/testing.py
primfunctions/completions/cache.py
primfunctions/completions/messages.py
primfunctions/completions/request.py
primfunctions/completions/response.py
primfunctions/completions/streaming.py
primfunctions/utils/__init__.py
primfunctions/utils/errors.py
primfunctions/utils/streaming.py
primfunctions-0.1.72.dist-info/METADATA
primfunctions-0.1.72.dist-info/WHEEL
primfunctions-0.1.72.dist-info/top_level.txt
primfunctions-0.1.72.dist-info/RECORD
