Metadata-Version: 2.4
Name: primfunctions
Version: 0.1.72
Summary: Prim AI Functions
Author-email: Prim AI <derek@primai.com>
Requires-Python: >=3.10
Requires-Dist: black>=23.3.0
